der_die_das/__init__.py
der_die_das-0.0.1.dist-info/LICENSE
der_die_das-0.0.1.dist-info/METADATA
der_die_das-0.0.1.dist-info/WHEEL
der_die_das-0.0.1.dist-info/top_level.txt
der_die_das-0.0.1.dist-info/zip-safe
der_die_das-0.0.1.dist-info/RECORD
