Metadata-Version: 2.1
Name: der-die-das
Version: 0.0.1
Summary: Python Library for DER DIE DAS APP
Home-page: https://github.com/yuyatinnefeld/der_die_das
Author: yuya tinnefeld
Author-email: yuyatinnefeld@gmail.com
License: Copyright (c) 2022 Yuya Tinnefeld
Project-URL: Bug Tracker, https://github.com/yuyatinnefeld/der_die_das/issues
Platform: UNKNOWN
Classifier: Development Status :: 3 - Alpha
Classifier: Programming Language :: Python :: 3.7
Requires-Python: >=3.7
License-File: LICENSE
Requires-Dist: beautifulsoup4 (==4.10.0)
Requires-Dist: requests (==2.26.0)
